atarg/__init__.py
atarg/execute.py
atarg/main.py
atarg/parse_html.py
atarg-1.0.1.data/scripts/atarg
atarg-1.0.1.dist-info/METADATA
atarg-1.0.1.dist-info/RECORD
atarg-1.0.1.dist-info/WHEEL
atarg-1.0.1.dist-info/top_level.txt
