Metadata-Version: 2.1
Name: atarg
Version: 1.0.1
Summary: Testing tool before submit for atcoder
Home-page: https://github.com/itto-ki/Atarg/
Author: Ittoh Kimura
Author-email: kimura.itto.kd3@gmail.com
License: MIT
Platform: UNKNOWN
Classifier: Development Status :: 4 - Beta
Classifier: Environment :: Console
Classifier: License :: OSI Approved :: MIT License
Classifier: Programming Language :: Python :: 3
Classifier: Topic :: Internet :: WWW/HTTP
Classifier: Topic :: Software Development
Classifier: Topic :: Utilities
Requires-Dist: requests
Requires-Dist: beautifulsoup4
